{
  "category": "セキュリティ",
  "categoryId": "security",
  "questions": [
    {
      "id": 1,
      "story": "紬は店の帳場に三つの鍵を掛けた。『内緒を守り（機密性）、壊れがないか確かめ（完全性）、いつでも使えるように（可用性）』。凪はそれを三本柱と呼んだ。",
      "question": "情報セキュリティの三要素（CIA）として正しい組はどれですか？",
      "options": [
        "機密性・完全性・可用性",
        "機密性・匿名性・迅速性",
        "真正性・匿名性・冗長性",
        "完全性・拡張性・互換性"
      ],
      "correctAnswer": 0,
      "explanation": "CIAはConfidentiality（機密性）、Integrity（完全性）、Availability（可用性）の三要素です。",
      "difficulty": "初級",
      "tags": ["CIA", "基礎"],
      "relatedChapter": 1
    },
    {
      "id": 2,
      "story": "港の電信は聞き耳に注意が要る。『封をして運べば途中で読まれにくい』と凪。",
      "question": "HTTPS（HTTP over TLS）の主な利点として最も適切なのはどれですか？",
      "options": [
        "通信内容の暗号化と改ざん検出、サーバ認証が可能になる",
        "常に通信速度が上がる",
        "サーバの負荷が必ず下がる",
        "ブラウザキャッシュが無効化される"
      ],
      "correctAnswer": 0,
      "explanation": "TLSにより暗号化・改ざん検出・証明書によるサーバ認証が提供されます。",
      "difficulty": "初級",
      "tags": ["HTTPS", "TLS"],
      "relatedChapter": 2
    },
    {
      "id": 3,
      "story": "貼り紙の隙間から悪戯書きが混ざると困る。『刷る前に余計な記号を逃がすのが肝要』と女将。",
      "question": "XSS（クロスサイトスクリプティング）対策の基本として最も適切なのはどれですか？",
      "options": [
        "信頼できないデータをHTMLへ出力する際に適切なエスケープを行う",
        "DBを毎晩バックアップする",
        "画像は必ず圧縮する",
        "JavaScriptを全て禁止する"
      ],
      "correctAnswer": 0,
      "explanation": "出力コンテキストに応じたエスケープ（HTML/属性/URL/JS）やテンプレートの自動エスケープが基本です。",
      "difficulty": "初級",
      "tags": ["XSS", "エスケープ"],
      "relatedChapter": 3
    },
    {
      "id": 4,
      "story": "勝手に送られた書付で注文が通ってしまうと困る。『本人しか書けない印（トークン）を添えるのだ』と凪。",
      "question": "CSRF対策として有効な方法はどれですか？",
      "options": [
        "CSRFトークンの検証を行う",
        "画像をWebPにする",
        "CDNを導入する",
        "ブラウザの戻るボタンを無効化する"
      ],
      "correctAnswer": 0,
      "explanation": "状態変更リクエストに対して予測困難なトークンを検証するのが基本対策です。SameSite Cookieの設定も有効です。",
      "difficulty": "初級",
      "tags": ["CSRF", "トークン", "SameSite"],
      "relatedChapter": 3
    },
    {
      "id": 5,
      "story": "帳面の控えは盗み見られても読めぬように『塩（ソルト）を混ぜて印（ハッシュ）にする』と女将。",
      "question": "ユーザパスワードの保存方法として最も適切なのはどれですか？",
      "options": [
        "個別ソルト付きのストレッチング可能なハッシュ（例: bcrypt/argon2）で保存する",
        "平文で保存する",
        "MD5でソルトなしハッシュ",
        "対称鍵で暗号化して平文復元できる形で保存"
      ],
      "correctAnswer": 0,
      "explanation": "bcrypt/argon2/scryptなど、ソルト付き・計算コスト調整可能なハッシュで保存するのが推奨です。",
      "difficulty": "中級",
      "tags": ["パスワード", "ハッシュ", "ソルト"],
      "relatedChapter": 4
    },
    {
      "id": 6,
      "story": "帳面に文字をそのまま差し込むと乱れる。『穴を用意して値だけ渡すと安全だ』と凪。",
      "question": "SQLインジェクション対策として最も適切なのはどれですか？",
      "options": [
        "プリペアドステートメント（バインド変数）を使用する",
        "SELECT文をすべて大文字にする",
        "文字数制限だけを設ける",
        "DBを毎日再起動する"
      ],
      "correctAnswer": 0,
      "explanation": "クエリとデータを分離するプリペアドステートメントが基本対策です。",
      "difficulty": "初級",
      "tags": ["SQLi", "プリペアドステートメント"],
      "relatedChapter": 4
    },
    {
      "id": 7,
      "story": "札を渡す番所では、身分が通ったら新しい通行札に取り替える。古い札のままでは盗用されかねない。",
      "question": "セッション固定攻撃（Session Fixation）への対策として適切なのはどれですか？",
      "options": [
        "ログイン成功時にセッションIDを再発行する",
        "画像に透かしを入れる",
        "毎回ログを消去する",
        "CSSを圧縮する"
      ],
      "correctAnswer": 0,
      "explanation": "認証直後のセッションIDローテーション（再発行）は基本的な対策です。",
      "difficulty": "中級",
      "tags": ["セッション固定", "セッションID"],
      "relatedChapter": 5
    },
    {
      "id": 8,
      "story": "『あなたは誰か』と『あなたに何を任せるか』は別の話だと凪は言う。",
      "question": "認証と認可の説明として正しい組み合わせはどれですか？",
      "options": [
        "認証=利用者の本人確認 / 認可=権限付与・アクセス制御",
        "認証=権限付与 / 認可=本人確認",
        "両方とも本人確認",
        "両方とも暗号化"
      ],
      "correctAnswer": 0,
      "explanation": "Authenticationは『誰か』、Authorizationは『何をしてよいか』に関する仕組みです。",
      "difficulty": "初級",
      "tags": ["認証", "認可"],
      "relatedChapter": 2
    },
    {
      "id": 9,
      "story": "『印は元に戻せぬから印で、封は開ければ読めるから封なのだ』と女将。",
      "question": "ハッシュと暗号の主な違いとして正しいのはどれですか？",
      "options": [
        "ハッシュは一方向で復元できず、暗号は復号で元に戻せる",
        "どちらも復元できない",
        "どちらも復元できる",
        "ハッシュは暗号より必ず強い"
      ],
      "correctAnswer": 0,
      "explanation": "ハッシュは一方向関数で原像復元を前提としません。暗号は鍵により復号が可能です。",
      "difficulty": "初級",
      "tags": ["ハッシュ", "暗号"],
      "relatedChapter": 4
    },
    {
      "id": 10,
      "story": "凪は『印は私が押し、確かめは皆ができる』と言った。秘密鍵と公開鍵の役割である。",
      "question": "公開鍵基盤で『デジタル署名』の正しい説明はどれですか？",
      "options": [
        "秘密鍵で署名し、公開鍵で検証する",
        "公開鍵で署名し、秘密鍵で検証する",
        "共通鍵で署名し、同じ鍵で検証する",
        "どの鍵でもよい"
      ],
      "correctAnswer": 0,
      "explanation": "署名は秘密鍵で作成し、対応する公開鍵で誰でも検証できます。",
      "difficulty": "中級",
      "tags": ["公開鍵", "署名", "PKI"],
      "relatedChapter": 6
    }
  ],
  "metadata": {
    "totalQuestions": 10,
    "difficulty": { "初級": 7, "中級": 3, "上級": 0 },
    "estimatedTime": "15分",
    "passingScore": 70,
    "tags": ["HTTPS", "TLS", "XSS", "CSRF", "SQLi", "パスワード", "認証/認可", "ハッシュ", "公開鍵基盤"]
  }
}
