{
  "id": 7,
  "title": "小数のゆらぎ",
  "icon": "07",
  "summary": "0.1+0.2≠0.3?—丸めと誤差の心得",
  "story": [
    "紬は反物の長さを小数で測る。だが三度計って三度微妙に違う。",
    "計算機の小数(浮動小数点)も、2進で厳密に表せない0.1のような値には近似が混ざる。",
    "0.1+0.2が0.30000000000000004のように見えるのは、その『近似』の寄せ集めだから。",
    "凪は『表示は四捨五入、内部は誤差を見越して比較』と伝える。",
    "測量でも許容誤差を決めて扱うのと同じだ。",
    "戦況の噂は誇張と省略で変形する。数字も噂も、丸め方と基準を決めて受け止めるのが上策だった。"
  ],
  "poem": {"title": "丸めの短歌","lines": ["ぴたりなど","世は稀なるを","知るほどに","許しの幅で","真を掬わん"]},
  "keyPoints": [
    { "term": "浮動小数点", "definition": "小数を近似で表す方式。桁数に限りがあるため誤差が生じうる" },
    { "term": "丸め", "definition": "表示や計算の段で桁を整えること" }
  ]
}
